.gitignore
CHANGES.rst
LICENSE.GPL
LICENSE.txt
MANIFEST.in
README.rst
bootstrap.py
buildout.cfg
development.ini
ldap.ini
production.ini
setup.cfg
setup.py
who.ini
./osiris/__init__.py
./osiris/appconst.py
./osiris/authorization.py
./osiris/endpoints.py
./osiris/errorhandling.py
./osiris/generator.py
./osiris/store/__init__.py
./osiris/store/interface.py
./osiris/store/mongodb_store.py
./osiris/tests/__init__.py
./osiris/tests/test_legacy.py
./osiris/tests/tests.py
osiris/__init__.py
osiris/appconst.py
osiris/authorization.py
osiris/endpoints.py
osiris/errorhandling.py
osiris/generator.py
osiris.egg-info/PKG-INFO
osiris.egg-info/SOURCES.txt
osiris.egg-info/dependency_links.txt
osiris.egg-info/entry_points.txt
osiris.egg-info/not-zip-safe
osiris.egg-info/requires.txt
osiris.egg-info/top_level.txt
osiris/store/__init__.py
osiris/store/interface.py
osiris/store/mongodb_store.py
osiris/tests/__init__.py
osiris/tests/passwd
osiris/tests/test.ini
osiris/tests/test_legacy.py
osiris/tests/tests.py
osiris/tests/who.ini