Metadata-Version: 1.1
Name: osiris
Version: 1.4
Summary: Pyramid based oAuth server
Home-page: https://github.com/sneridagh/osiris.git
Author: Victor Fernandez de Alba
Author-email: sneridagh@gmail.com
License: UNKNOWN
Keywords: web pyramid pylons
Platform: UNKNOWN
Classifier: Programming Language :: Python
Classifier: Framework :: Pylons
Classifier: Topic :: Internet :: WWW/HTTP
Classifier: Topic :: Internet :: WWW/HTTP :: WSGI :: Application
